PyThat/__init__.py
PyThat/h5to_nc.py
PyThat/helpers/BLS.py
PyThat/helpers/Explorer.py
PyThat/helpers/FMR.py
PyThat/helpers/ROI.py
PyThat/helpers/__init__.py
PyThat/helpers/dB.py
PyThat/helpers/plotting.py
PyThat-0.2.14.dist-info/LICENSE.txt
PyThat-0.2.14.dist-info/METADATA
PyThat-0.2.14.dist-info/WHEEL
PyThat-0.2.14.dist-info/top_level.txt
PyThat-0.2.14.dist-info/RECORD
