Metadata-Version: 2.1
Name: PyThat
Version: 0.2.14
Summary: Read Thatec h5 formatting and convert it to netcdf files and xarray objects.
Home-page: https://github.com/mrschweizer/PyThat
Author: Matthias Schweizer
Author-email: mareschweizer@gmail.com
Project-URL: Bug Tracker, https://github.com/mrschweizer/PyThat/issues
Project-URL: Documentation, https://pythat.readthedocs.io/
Classifier: Programming Language :: Python :: 3
Classifier: License :: OSI Approved :: MIT License
Classifier: Operating System :: OS Independent
Requires-Python: >=3.7
License-File: LICENSE.txt
Requires-Dist: xarray >=0.17.0
Requires-Dist: numpy
Requires-Dist: scipy
Requires-Dist: h5py >=3.2.1
Requires-Dist: netcdf4
Requires-Dist: h5netcdf
Requires-Dist: matplotlib
Requires-Dist: PyYAML
Requires-Dist: dask
